FireSpark/__init__.py
FireSpark/core/__init__.py
FireSpark/core/aws_utils.py
FireSpark/core/data_utils.py
FireSpark/core/lyftbag_topics.py
FireSpark/core/lyftbag_utils.py
FireSpark/core/numpy_utils.py
FireSpark/core/proto_utils.py
FireSpark/core/query_utils.py
FireSpark/core/tensorflow_utils.py
FireSpark/core/torch_utils.py
FireSpark/datasets/__init__.py
FireSpark/datasets/dataset_lib.py
FireSpark/datasets/l5lmdb_image_lib.py
FireSpark/datasets/label_functions.py
FireSpark/datasets/lyftbag_image_lib.py
FireSpark/datasets/proto_image_lib.py
FireSpark/datasets/schemas.py
FireSpark/protos/__init__.py
FireSpark/protos/mas/__init__.py
FireSpark/protos/mas/annotation_pb2.py
FireSpark/protos/mas/devices_pb2.py
FireSpark/protos/mas/dtypes_pb2.py
FireSpark/protos/mas/image_data_pb2.py
FireSpark/protos/mas/labels_pb2.py
FireSpark/protos/mas/lyftbag_pb2.py
FireSpark/protos/src/__init__.py
FireSpark/protos/src/avs/__init__.py
FireSpark/protos/src/avs/messages/__init__.py
FireSpark/protos/src/avs/messages/carviz_timing_pb2.py
FireSpark/protos/src/avs/messages/diagnostic_id_pb2.py
FireSpark/protos/src/avs/messages/diagnostics_command_message_pb2.py
FireSpark/protos/src/avs/messages/diagnostics_message_pb2.py
FireSpark/protos/src/avs/messages/diagnostics_types_pb2.py
FireSpark/protos/src/avs/messages/disengagement_report_message_pb2.py
FireSpark/protos/src/avs/messages/guid_message_pb2.py
FireSpark/protos/src/avs/messages/lyft_car_time_pb2.py
FireSpark/protos/src/avs/messages/lyft_car_time_with_source_pb2.py
FireSpark/protos/src/avs/messages/lyftbag_pb2.py
FireSpark/protos/src/avs/messages/message_header_pb2.py
FireSpark/protos/src/avs/messages/microservice_event_stats_pb2.py
FireSpark/protos/src/avs/messages/mission_pb2.py
FireSpark/protos/src/avs/messages/perf_message_pb2.py
FireSpark/protos/src/avs/messages/plugin_statistics_pb2.py
FireSpark/protos/src/avs/messages/plugin_subscriber_statistics_pb2.py
FireSpark/protos/src/avs/messages/profile_message_pb2.py
FireSpark-0.0.32.dist-info/METADATA
FireSpark-0.0.32.dist-info/WHEEL
FireSpark-0.0.32.dist-info/top_level.txt
FireSpark-0.0.32.dist-info/RECORD
